instruments/__init__.py
instruments/config.py
instruments/errors.py
instruments/named_struct.py
instruments/units.py
instruments/util_fns.py
instruments/abstract_instruments/__init__.py
instruments/abstract_instruments/electrometer.py
instruments/abstract_instruments/function_generator.py
instruments/abstract_instruments/instrument.py
instruments/abstract_instruments/multimeter.py
instruments/abstract_instruments/optical_spectrum_analyzer.py
instruments/abstract_instruments/oscilloscope.py
instruments/abstract_instruments/power_supply.py
instruments/abstract_instruments/comm/__init__.py
instruments/abstract_instruments/comm/abstract_comm.py
instruments/abstract_instruments/comm/file_communicator.py
instruments/abstract_instruments/comm/gpib_communicator.py
instruments/abstract_instruments/comm/loopback_communicator.py
instruments/abstract_instruments/comm/serial_communicator.py
instruments/abstract_instruments/comm/serial_manager.py
instruments/abstract_instruments/comm/socket_communicator.py
instruments/abstract_instruments/comm/usb_communicator.py
instruments/abstract_instruments/comm/usbtmc_communicator.py
instruments/abstract_instruments/comm/visa_communicator.py
instruments/abstract_instruments/comm/vxi11_communicator.py
instruments/abstract_instruments/signal_generator/__init__.py
instruments/abstract_instruments/signal_generator/channel.py
instruments/abstract_instruments/signal_generator/signal_generator.py
instruments/abstract_instruments/signal_generator/single_channel_sg.py
instruments/agilent/__init__.py
instruments/agilent/agilent33220a.py
instruments/agilent/agilent34410a.py
instruments/fluke/__init__.py
instruments/fluke/fluke3000.py
instruments/generic_scpi/__init__.py
instruments/generic_scpi/scpi_function_generator.py
instruments/generic_scpi/scpi_instrument.py
instruments/generic_scpi/scpi_multimeter.py
instruments/glassman/__init__.py
instruments/glassman/glassmanfr.py
instruments/holzworth/__init__.py
instruments/holzworth/holzworth_hs9000.py
instrumentkit-0.6.0.dist-info/METADATA
instrumentkit-0.6.0.dist-info/WHEEL
instrumentkit-0.6.0.dist-info/top_level.txt
instrumentkit-0.6.0.dist-info/RECORD
